hack4u/__init__.py
hack4u/courses.py
hack4u/utils.py
pwn4u-0.5.2.dist-info/METADATA
pwn4u-0.5.2.dist-info/WHEEL
pwn4u-0.5.2.dist-info/top_level.txt
pwn4u-0.5.2.dist-info/RECORD
