Metadata-Version: 2.1
Name: pwn4u
Version: 0.5.2
Summary: Una biblioteca para consultar cursos de hack4u
Home-page: https://hack4u.io
Author: Cristian Hernández
